drugpy/__init__.py
drugpy/commons.py
drugpy/fetch_similar/__init__.py
drugpy/fetch_similar/blast.py
drugpy/fetch_similar/blast_gui.py
drugpy/fetch_similar/shape3d.py
drugpy/fetch_similar/shape3d_gui.py
drugpy/ftmap/__init__.py
drugpy/ftmap/core.py
drugpy/ftmap/gui.py
DRUGpy-1.1.0.dist-info/LICENSE.txt
DRUGpy-1.1.0.dist-info/METADATA
DRUGpy-1.1.0.dist-info/WHEEL
DRUGpy-1.1.0.dist-info/top_level.txt
DRUGpy-1.1.0.dist-info/RECORD
